pebble/__init__.py
pebble/decorators.py
pebble/functions.py
pebble/py.typed
pebble/asynchronous/__init__.py
pebble/asynchronous/process.py
pebble/asynchronous/thread.py
pebble/common/__init__.py
pebble/common/process.py
pebble/common/shared.py
pebble/common/types.py
pebble/concurrent/__init__.py
pebble/concurrent/process.py
pebble/concurrent/thread.py
pebble/pool/__init__.py
pebble/pool/base_pool.py
pebble/pool/channel.py
pebble/pool/process.py
pebble/pool/thread.py
pebble-5.2.0.dist-info/licenses/LICENSE
pebble-5.2.0.dist-info/METADATA
pebble-5.2.0.dist-info/WHEEL
pebble-5.2.0.dist-info/top_level.txt
pebble-5.2.0.dist-info/RECORD
