Metadata-Version: 2.4
Name: Pebble
Version: 5.2.0
Summary: Threading and multiprocessing eye-candy.
Home-page: https://github.com/noxdafox/pebble
Author: Matteo Cafasso
Author-email: noxdafox@gmail.com
License: LGPL
Keywords: thread process pool decorator
Classifier: Programming Language :: Python :: 3
Classifier: Development Status :: 5 - Production/Stable
Classifier: Intended Audience :: Developers
Classifier: Operating System :: OS Independent
Classifier: Topic :: Software Development :: Libraries :: Python Modules
Classifier: License :: OSI Approved :: GNU Library or Lesser General Public License (LGPL)
Requires-Python: >=3.8
License-File: LICENSE
Dynamic: author
Dynamic: author-email
Dynamic: classifier
Dynamic: description
Dynamic: home-page
Dynamic: keywords
Dynamic: license
Dynamic: license-file
Dynamic: requires-python
Dynamic: summary
